{
    "fa": {
        "filemanager": {
            "NewFolder": "پوشه جدید",
            "Upload": "بارگذاری",
            "Delete": "حذف",
            "Rename": "تغییر نام دهید",
            "Download": "دانلود",
            "Cut": "برش",
            "Copy": "کپی کنید",
            "Paste": "چسباندن",
            "SortBy": "مرتب سازی بر اساس",
            "Refresh": "تازه کردن",
            "Selection": "اقلام انتخاب شده",
            "View": "چشم انداز",
            "Details": "جزئیات",
            "SelectAll": "انتخاب همه",
            "Open": "باز کن",
            "Tooltip-NewFolder": "پوشه جدید",
            "Tooltip-Upload": "بارگذاری",
            "Tooltip-Delete": "حذف",
            "Tooltip-Rename": "تغییر نام دهید",
            "Tooltip-Download": "دانلود",
            "Tooltip-Cut": "برش",
            "Tooltip-Copy": "کپی کنید",
            "Tooltip-Paste": "چسباندن",
            "Tooltip-SortBy": "مرتب سازی بر اساس",
            "Tooltip-Refresh": "تازه کردن",
            "Tooltip-Selection": "پاک کردن انتخاب",
            "Tooltip-View": "چشم انداز",
            "Tooltip-Details": "جزئیات",
            "Tooltip-SelectAll": "انتخاب همه",
            "Name": "نام",
            "Size": "اندازه",
            "DateModified": "اصلاح شده",
            "DateCreated": "تاریخ ایجاد",
            "Created": "ایجاد شده",
            "Modified": "اصلاح شده",
            "Location": "محل",
            "Type": "تایپ کنید",
            "Ascending": "صعودی",
            "Descending": "نزولی",
            "View-LargeIcons": "آیکون های بزرگ",
            "View-Details": "جزئیات",
            "Search": "جستجو همه چیز",
            "Button-Ok": "خوب",
            "Button-Cancel": "لغو",
            "Button-Yes": "بله",
            "Button-No": "نه",
            "Button-Create": "ايجاد كردن",
            "Button-Save": "صرفه جویی",
            "Header-NewFolder": "پوشه",
            "Content-NewFolder": "نام پوشه خود را وارد کنید",
            "Header-Rename": "تغییر نام دهید",
            "Content-Rename": "نام جدید خود را وارد کنید",
            "Header-Rename-Confirmation": "تغییر نام تأیید",
            "Content-Rename-Confirmation": "اگر یک پسوند نام فایل را تغییر دهید، فایل ممکن است ناپایدار شود. آیا مطمئن هستید که می خواهید آن را تغییر دهید؟",
            "Header-Delete": "حذف فایل",
            "Content-Delete": "آیا مطمئن هستید که می خواهید این فایل را حذف کنید؟",
            "Header-Multiple-Delete": "چندین فایل را حذف کنید",
            "Content-Multiple-Delete": "آیا مطمئنید که میخواهید این فایلهای {0} را حذف کنید؟",
            "Header-Details": "جزئیات فایل",
            "Header-Multiple-Details": "جزئیات فایل",
            "Header-Duplicate": "فایل وجود دارد",
            "Content-Duplicate": " درحال حاضر وجود دارد. آیا مطمئن هستید که می خواهید آن را جایگزین کنید؟",
            "Error": "خطا",
            "Validation-Empty": "نام فایل یا پوشه نباید خالی باشد.",
            "Validation-Invalid": "نام فایل یا پوشه {0} حاوی نویسه های نامعتبر است. لطفا از نام دیگری استفاده کنید. نام پرونده یا پوشه معتبر نمی تواند با نقطه یا فضای خاتمه نیافته و نتواند حاوی هیچیک از کاراکترهای زیر باشد: \\ /: *؟ \"<> |",
            "Validation-NewFolder-Exists": "یک فایل یا پوشه با نام {0} در حال حاضر وجود دارد.",
            "Validation-Rename-Exists": "{0} را به {1} تغییر نام نمی دهیم: مقصد قبلا وجود دارد.",
            "Folder-Empty": "این پوشه خالی است",
            "File-Upload": "برای آپلود فایل های اینجا را بکشید",
            "Search-Empty": "نتیجه ای پیدا نشد",
            "Search-Key": "با کلمات کلیدی مختلف سعی کنید"
        },
        "querybuilder": {
            "StartsWith": "شروع می شود با",
            "EndsWith": "به پایان می رسد با",
            "Contains": "شامل",
            "Equal": "برابر",
            "NotEqual": "نا برابر",
            "LessThan": "کمتر از",
            "LessThanOrEqual": "کمتر یا مساوی",
            "GreaterThan": "بزرگتر از",
            "GreaterThanOrEqual": "بزرگتر یا مساوی",
            "Between": "بین",
            "NotBetween": "نه بین",
            "Empty": "خالی",
            "NotEmpty": "خالی نیست",
            "In": "که در",
            "NotIn": "نه در",
            "NotContains": "شامل نمی شود",
            "Remove": "برداشتن",
            "SelectField": "یک فیلد را انتخاب کنید",
            "SelectOperator": "اپراتور را انتخاب کنید",
            "DeleteRule": "این شرایط را حذف کنید",
            "DeleteGroup": "حذف گروه",
            "AddGroup": "اضافه کردن گروه",
            "AddCondition": "اضافه کردن شرط",
            "Edit": "ویرایش کنید",
            "ValidationMessage": "این فیلد مورد نیاز است",
            "SummaryViewTitle": "خلاصه نمایش"
        },
        "grid": {
            "EmptyRecord": "هیچ پرونده برای نمایش نیست",
            "True": "درست است",
            "False": "نادرست",
            "InvalidFilterMessage": "داده های فیلتر نامعتبر",
            "GroupDropArea": "در اینجا ستون هدر را برای گروه بندی ستون خود بکشید",
            "UnGroup": "برای ungroup اینجا کلیک کنید",
            "GroupDisable": "گروه بندی برای این ستون غیر فعال است",
            "FilterbarTitle": "سلول فیلتر نوار فیلتر",
            "EmptyDataSourceError": "DataSource در بار اولیه نباید خالی باشد زیرا ستونها از dataSource در Grid ستون Auto Generate تولید می شوند",
            "Add": "اضافه کردن",
            "Edit": "ویرایش کنید",
            "Cancel": "لغو",
            "Update": "به روز رسانی",
            "Delete": "حذف",
            "Print": "چاپ",
            "Pdfexport": "صادرات PDF",
            "Excelexport": "اکسل صادرات",
            "Wordexport": "صادرات ورد",
            "Csvexport": "صادرات CSV",
            "Search": "جستجو کردن",
            "Columnchooser": "ستون ها",
            "Save": "صرفه جویی",
            "Item": "آیتم",
            "Items": "موارد",
            "EditOperationAlert": "هیچ رکوردی برای عملیات ویرایش انتخاب نشده است",
            "DeleteOperationAlert": "هیچ پرونده ای برای عملیات حذف انتخاب نشده است",
            "SaveButton": "صرفه جویی",
            "OKButton": "خوب",
            "CancelButton": "لغو",
            "EditFormTitle": "جزئیات",
            "AddFormTitle": "اضافه کردن رکورد جدید",
            "BatchSaveConfirm": "آیا مطمئن هستید که میخواهید تغییرات را ذخیره کنید؟",
            "BatchSaveLostChanges": "تغییرات ذخیره نشده از دست خواهد رفت. آیا مطمئن هستید که میخواهید ادامه دهید؟",
            "ConfirmDelete": "آیا مطمئن هستید که میخواهید رکورد را حذف کنید؟",
            "CancelEdit": "آیا مطمئن هستید که میخواهید تغییرات را لغو کنید؟",
            "ChooseColumns": "ستون را انتخاب کنید",
            "SearchColumns": "ستون جستجو",
            "Matchs": "جستجو حاصلی دربرنداشت",
            "FilterButton": "فیلتر کردن",
            "ClearButton": "پاک کردن",
            "StartsWith": "شروع می شود با",
            "EndsWith": "به پایان می رسد با",
            "Contains": "شامل",
            "Equal": "برابر",
            "NotEqual": "نا برابر",
            "LessThan": "کمتر از",
            "LessThanOrEqual": "کمتر یا مساوی",
            "GreaterThan": "بزرگتر از",
            "GreaterThanOrEqual": "بزرگتر یا مساوی",
            "ChooseDate": "یک تاریخ را انتخاب کنید",
            "EnterValue": "مقدار را وارد کنید",
            "Copy": "کپی کنید",
            "Group": "گروه با این ستون",
            "Ungroup": "با این ستون گروه بندی کنید",
            "autoFitAll": "خودکار تمام ستونها را مناسب کنید",
            "autoFit": "خودکار متناسب با این ستون",
            "Export": "صادرات",
            "FirstPage": "صفحه اول",
            "LastPage": "آخرین صفحه",
            "PreviousPage": "صفحه قبلی",
            "NextPage": "صفحه بعد",
            "SortAscending": "ترتیب صعودی",
            "SortDescending": "ترتیب نزولی",
            "EditRecord": "ویرایش ضبط",
            "DeleteRecord": "حذف ضبط",
            "FilterMenu": "فیلتر کردن",
            "SelectAll": "انتخاب همه",
            "Blanks": "صفات",
            "FilterTrue": "درست است",
            "FilterFalse": "اشتباه",
            "NoResult": "جستجو حاصلی دربرنداشت",
            "ClearFilter": "پاک کردن فیلتر",
            "NumberFilter": "فیلترهای شماره",
            "TextFilter": "فیلترهای متن",
            "DateFilter": "فیلترهای تاریخ",
            "DateTimeFilter": "فیلترهای DateTime",
            "MatchCase": "مسابقه مورد",
            "Between": "بین",
            "CustomFilter": "فیلتر سفارشی",
            "CustomFilterPlaceHolder": "مقدار را وارد کنید",
            "CustomFilterDatePlaceHolder": "یک تاریخ را انتخاب کنید",
            "AND": "و",
            "OR": "یا",
            "ShowRowsWhere": "نمایش ردیف که در آن:"
        },
        "pager": {
            "currentPageInfo": "{0} از {1} صفحات",
            "totalItemsInfo": "({0} آیتم)",
            "firstPageTooltip": "برو به صفحه اول",
            "lastPageTooltip": "برو به آخرین صفحه",
            "nextPageTooltip": "برو به صفحه بعدی",
            "previousPageTooltip": "برو به صفحه قبلی",
            "nextPagerTooltip": "به پیجر بعدی بروید",
            "previousPagerTooltip": "به پیجر قبلی بروید",
            "pagerDropDown": "اقلام در هر صفحه",
            "pagerAllDropDown": "موارد",
            "All": "همه"
        },
        "tab": {
            "closeButtonTitle": "نزدیک"
        },
        "DocumentEditor": {
            "Table": "جدول",
            "Row": "ردیف",
            "Cell": "سلول",
            "Ok": "خوب",
            "Cancel": "لغو",
            "Size": "اندازه",
            "Preferred Width": "عرض انتخابی",
            "Points": "نکته ها",
            "Percent": "درصد",
            "Measure in": "اندازه گیری در",
            "Alignment": "هم ترازی",
            "Left": "ترک کرد",
            "Center": "مرکز",
            "Right": "درست",
            "Justify": "توجیه",
            "Indent from left": "عقب سمت چپ",
            "Borders and Shading": "مرزها و سایه",
            "Options": "گزینه ها",
            "Specify height": "ارتفاع را مشخص کنید",
            "At least": "حداقل",
            "Exactly": "دقیقا",
            "Row height is": "ارتفاع ردیف است",
            "Allow row to break across pages": "اجازه ردیف را برای شکستن صفحات",
            "Repeat as header row at the top of each page": "تکرار به عنوان ردیف سرصفحه در بالای هر صفحه",
            "Vertical alignment": "چیدمان عمودی",
            "Top": "بالا",
            "Bottom": "پایین",
            "Default cell margins": "حاشیه های پیش فرض سلول",
            "Default cell spacing": "فاصله پیش فرض سلول",
            "Allow spacing between cells": "اجازه فاصله بین سلول ها",
            "Cell margins": "حاشیه های سلولی",
            "Same as the whole table": "همانند کل جدول",
            "Borders": "مرز ها",
            "None": "هیچ یک",
            "Single": "تنها",
            "Dot": "نقطه",
            "DashSmallGap": "DashSmallGap",
            "DashLargeGap": "DashLargeGap",
            "DashDot": "DashDot",
            "DashDotDot": "DashDotDot",
            "Double": "دو برابر",
            "Triple": "سه گانه",
            "ThinThickSmallGap": "ThinThickSmallGap",
            "ThickThinSmallGap": "ThickThinSmallGap",
            "ThinThickThinSmallGap": "ThinThickThinSmallGap",
            "ThinThickMediumGap": "ThinThickMediumGap",
            "ThickThinMediumGap": "ThickThinMediumGap",
            "ThinThickThinMediumGap": "ThinThickThinMediumGap",
            "ThinThickLargeGap": "ThinThickLargeGap",
            "ThickThinLargeGap": "ThickThinLargeGap",
            "ThinThickThinLargeGap": "ThinThickThinLargeGap",
            "SingleWavy": "SingleWavy",
            "DoubleWavy": "DoubleWavy",
            "DashDotStroked": "DashDotStroked",
            "Emboss3D": "Emboss3D",
            "Engrave3D": "Engrave3D",
            "Outset": "پیشرو",
            "Inset": "درج",
            "Thick": "ضخیم",
            "Style": "سبک",
            "Width": "عرض",
            "Height": "ارتفاع",
            "Letter": "نامه",
            "Tabloid": "تبلوید",
            "Legal": "قانونی",
            "Statement": "بیانیه",
            "Executive": "اجرایی",
            "A3": "A3",
            "A4": "A4",
            "A5": "A5",
            "B4": "B4",
            "B5": "B5",
            "Custom Size": "اندازه سفارشی",
            "Different odd and even": "مختلف عجیب و غریب و حتی",
            "Different first page": "صفحه اول متفاوت",
            "From edge": "از لبه",
            "Header": "سرتیتر",
            "Footer": "پاورقی",
            "Margin": "حاشیه",
            "Paper": "کاغذ",
            "Layout": "طرح",
            "Orientation": "گرایش",
            "Landscape": "چشم انداز",
            "Portrait": "پرتره",
            "Table Of Contents": "جدول محتوا",
            "Show page numbers": "نمایش شماره های صفحه",
            "Right align page numbers": "راست بردن شماره صفحات",
            "Nothing": "هیچ چی",
            "Tab leader": "رهبر تب",
            "Show levels": "نمایش سطوح",
            "Use hyperlinks instead of page numbers": "از لینک ها به جای اعداد صفحه استفاده کنید",
            "Build table of contents from": "ساختن جدول محتویات از",
            "Styles": "سبک ها",
            "Available styles": "سبک های موجود",
            "TOC level": "سطح TOC",
            "Heading": "سرصفحه",
            "List Paragraph": "پاراگراف فهرست",
            "Normal": "طبیعی",
            "Outline levels": "سطح افقی",
            "Table entry fields": "زمینه ورودی جدول",
            "Modify": "تغییر",
            "Color": "رنگ",
            "Setting": "تنظیمات",
            "Box": "جعبه",
            "All": "همه",
            "Custom": "سفارشی",
            "Preview": "پیش نمایش",
            "Shading": "سایه",
            "Fill": "پر کنید",
            "Apply To": "به درخواست",
            "Table Properties": "خواص جدول",
            "Cell Options": "گزینه های سلولی",
            "Table Options": "گزینه های جدول",
            "Insert Table": "جدول را وارد کنید",
            "Number of columns": "تعداد ستون ها",
            "Number of rows": "تعداد ردیف ها",
            "Text to display": "متن برای نمایش",
            "Address": "نشانی",
            "Insert Hyperlink": "درج لینک",
            "Edit Hyperlink": "ویرایش لینک",
            "Insert": "قرار دادن",
            "General": "عمومی",
            "Indentation": "افتادن",
            "Before text": "قبل از متن",
            "Special": "ویژه",
            "First line": "خط اول",
            "Hanging": "آویزان",
            "After text": "بعد از متن",
            "By": "توسط",
            "Before": "قبل از",
            "Line Spacing": "فاصله خطوط",
            "After": "بعد از",
            "At": "در",
            "Multiple": "چندگانه",
            "Spacing": "فاصله",
            "Define new Multilevel list": "تعریف لیست چند لایه جدید",
            "List level": "سطح لیست",
            "Choose level to modify": "سطح را برای اصلاح انتخاب کنید",
            "Level": "سطح",
            "Number format": "فرمت شماره",
            "Number style for this level": "سبک شماره برای این سطح",
            "Enter formatting for number": "فرمت را برای شماره وارد کنید",
            "Start at": "شروع کن در",
            "Restart list after": "راه اندازی مجدد لیست پس از",
            "Position": "موقعیت",
            "Text indent at": "متن درج شده است",
            "Aligned at": "هماهنگ شده در",
            "Follow number with": "شماره را با دنبال کنید",
            "Tab character": "شخصیت تب",
            "Space": "فضا",
            "Arabic": "عربی",
            "UpRoman": "UpRoman",
            "LowRoman": "LowRoman",
            "UpLetter": "UpLetter",
            "LowLetter": "LowLetter",
            "Number": "عدد",
            "Leading zero": "صفر صفر",
            "Bullet": "گلوله",
            "Ordinal": "عادی",
            "Ordinal Text": "متن معمولی",
            "For East": "برای شرق",
            "No Restart": "بدون راه اندازی مجدد",
            "Font": "فونت",
            "Font style": "نوع قلم",
            "Underline style": "سبک زیرک",
            "Font color": "رنگ فونت",
            "Effects": "اثرات",
            "Strikethrough": "از بین بردن",
            "Superscript": "فوق ستاره",
            "Subscript": "زیرنویس",
            "Double strikethrough": "دوبرابر کردن",
            "Regular": "منظم",
            "Bold": "پررنگ",
            "Italic": "Italic",
            "Cut": "برش",
            "Copy": "کپی کنید",
            "Paste": "چسباندن",
            "Hyperlink": "لینک بالا",
            "Open Hyperlink": "باز Hyperlink",
            "Copy Hyperlink": "کپی Hyperlink",
            "Remove Hyperlink": "حذف Hyperlink",
            "Paragraph": "پاراگراف",
            "Merge Cells": "ادغام سلول ها",
            "Insert Above": "بالا وارد کنید",
            "Insert Below": "در زیر وارد کنید",
            "Insert Left": "درج چپ",
            "Insert Right": "راست را وارد کنید",
            "Delete": "حذف",
            "Delete Table": "حذف جدول",
            "Delete Row": "حذف ردیف",
            "Delete Column": "حذف ستون",
            "File Name": "نام فایل",
            "Format Type": "نوع فرمت",
            "Save": "صرفه جویی",
            "Navigation": "جهت یابی",
            "Results": "نتایج",
            "Replace": "جایگزین کردن",
            "Replace All": "جایگزین همه",
            "We replaced all": "همه ما را جایگزین کردیم",
            "Find": "پیدا کردن",
            "No matches": "هیچ بازی",
            "All Done": "همه انجام شده است",
            "Result": "نتیجه",
            "of": "از",
            "instances": "نمونه ها",
            "with": "با",
            "Click to follow link": "برای پیگیری کلیک کنید",
            "Continue Numbering": "شماره گیری ادامه دهید",
            "Bookmark name": "نام نشانگر",
            "Close": "نزدیک",
            "Restart At": "راه اندازی مجدد",
            "Properties": "خواص",
            "Name": "نام",
            "Style type": "نوع سبک",
            "Style based on": "سبک بر اساس",
            "Style for following paragraph": "سبک برای پاراگراف زیر",
            "Formatting": "فرمت کردن",
            "Numbering and Bullets": "شماره و گلوله",
            "Numbering": "شماره گذاری",
            "Update Field": "فیلد بهروزرسانی",
            "Edit Field": "ویرایش فیلد",
            "Bookmark": "چوب الف",
            "Page Setup": "تنظیمات صفحه",
            "No bookmarks found": "هیچ نشانک یافت نشد",
            "Number format tooltip information": "فرمت شماره یک: </ br> [PREFIX]٪ [LEVELNUMBER] [SUFFIX] </ br> به عنوان مثال، فصل٪ 1. عدد شماره مانند </ br> را نشان می دهد. </ br> فصل 1. مورد </ br> فصل 2. مورد </ br> ... </ br> فصل N عنصر </ br> </ br> فرمت شماره چندسطحی: </ br > [PREFIX]٪ [LEVELNUMBER] [SUFFIX] + [PREFIX]٪ [LEVELNUMBER] [SUFFIX] </ br> برای مثال،٪ 1.٪ 2. عددی مانند </ br> 1.1 نمایش داده خواهد شد. مورد </ br> 1.2. مورد </ br> ... </ br> 1.N. مورد",
            "Format": "فرمت",
            "Create New Style": "ایجاد سبک جدید",
            "Modify Style": "اصلاح سبک",
            "New": "جدید",
            "Bullets": "گلوله ها",
            "Use bookmarks": "استفاده از بوک مارک ها",
            "Table of Contents": "جدول محتوا"
        },
        "calendar": {
            "today": "امروز"
        },
        "datepicker": {
            "today": "امروز",
            "placeholder": "یک تاریخ را انتخاب کنید"
        },
        "daterangepicker": {
            "placeholder": "محدوده تاریخ را انتخاب کنید",
            "startLabel": "تاریخ شروع",
            "endLabel": "تاریخ پایان",
            "applyText": "درخواست دادن",
            "cancelText": "لغو",
            "selectedDays": "روزهای انتخاب شده",
            "days": "روزها",
            "customRange": "محدوده سفارشی"
        },
        "timepicker": {
            "placeholder": "یک زمان را انتخاب کنید"
        },
        "datetimepicker": {
            "today": "امروز",
            "placeholder": "یک تاریخ و زمان را انتخاب کنید"
        },
        "richtexteditor": {
            "alignments": "سازگاری",
            "justifyLeft": "تراز چپ",
            "justifyCenter": "مرکز هماهنگی",
            "justifyRight": "راست راست کن",
            "justifyFull": "تراز کردن",
            "fontName": "نام فونت",
            "fontSize": "اندازه فونت",
            "fontColor": "رنگ فونت",
            "backgroundColor": "رنگ پس زمینه",
            "bold": "پررنگ",
            "italic": "Italic",
            "underline": "زیر خط دار",
            "strikethrough": "از بین بردن",
            "clearFormat": "فرمت پاک کردن",
            "clearAll": "همه را پاک کن",
            "cut": "برش",
            "copy": "کپی کنید",
            "paste": "چسباندن",
            "unorderedList": "فهرست گلوله",
            "orderedList": "فهرست شماره گذاری شده",
            "indent": "افزایش تند",
            "outdent": "کاهش تند",
            "undo": "لغو",
            "redo": "دوباره بکش",
            "superscript": "فوق ستاره",
            "subscript": "زیرنویس",
            "createLink": "درج لینک",
            "openLink": "لینک های باز",
            "editLink": "ویرایش پیوند",
            "removeLink": "پیوند را حذف کنید",
            "image": "درج تصویر",
            "replace": "جایگزین کردن",
            "align": "هماهنگ کردن",
            "caption": "عنوان تصویر",
            "remove": "برداشتن",
            "insertLink": "لینک را وارد کنید",
            "display": "نمایش دادن",
            "altText": "متن جایگزین",
            "dimension": "تغییر اندازه",
            "fullscreen": "حداکثر کردن",
            "maximize": "حداکثر کردن",
            "minimize": "به حداقل رساندن",
            "lowerCase": "مورد پایینتر",
            "upperCase": "مورد بالا",
            "print": "چاپ",
            "formats": "فرمت ها",
            "sourcecode": "کد نمایش",
            "preview": "پیش نمایش",
            "viewside": "ViewSide",
            "insertCode": "کد را وارد کنید",
            "linkText": "نمایش متن",
            "linkTooltipLabel": "عنوان",
            "linkWebUrl": "آدرس وب",
            "linkTitle": "عنوان را وارد کنید",
            "linkurl": "http://example.com",
            "linkOpenInNewWindow": "لینک را در پنجره جدید باز کنید",
            "linkHeader": "لینک را وارد کنید",
            "dialogInsert": "قرار دادن",
            "dialogCancel": "لغو",
            "dialogUpdate": "به روز رسانی",
            "imageHeader": "درج تصویر",
            "imageLinkHeader": "شما همچنین می توانید یک لینک از وب فراهم کنید",
            "mdimageLink": "لطفا برای تصویر خود یک URL بگذارید",
            "imageUploadMessage": "قطره عکس اینجا و یا فهرست برای آپلود",
            "imageDeviceUploadMessage": "برای آپلود اینجا کلیک کنید",
            "imageAlternateText": "متن جایگزین",
            "alternateHeader": "متن جایگزین",
            "browse": "مرور کردن",
            "imageUrl": "http://example.com/image.png",
            "imageCaption": "عنوان",
            "imageSizeHeader": "اندازه تصویر",
            "imageHeight": "ارتفاع",
            "imageWidth": "عرض",
            "textPlaceholder": "متن را وارد کنید",
            "inserttablebtn": "جدول را وارد کنید",
            "tabledialogHeader": "جدول را وارد کنید",
            "tableWidth": "عرض",
            "cellpadding": "پلاستیکی سلولی",
            "cellspacing": "فاصله سلول",
            "columns": "تعداد ستون ها",
            "rows": "تعداد ردیف ها",
            "tableRows": "جدول جدول",
            "tableColumns": "ستون های جدول",
            "tableCellHorizontalAlign": "ستون افقی ستون جدول جدول",
            "tableCellVerticalAlign": "جدول متحرک جدول عمودی",
            "createTable": "ایجاد جدول",
            "removeTable": "حذف جدول",
            "tableHeader": "سربرگ جدول",
            "tableRemove": "حذف جدول",
            "tableCellBackground": "پس زمینه جدول سلول",
            "tableEditProperties": "جدول خواص ویرایش",
            "styles": "سبک ها",
            "insertColumnLeft": "درج ستون سمت چپ",
            "insertColumnRight": "ستون راست را وارد کنید",
            "deleteColumn": "حذف ستون",
            "insertRowBefore": "قبل از وارد کردن ردیف",
            "insertRowAfter": "درج ردیف بعد",
            "deleteRow": "حذف ردیف",
            "tableEditHeader": "ویرایش جدول",
            "TableHeadingText": "سرصفحه",
            "TableColText": "سرهنگ",
            "imageInsertLinkHeader": "لینک را وارد کنید",
            "editImageHeader": "ویرایش تصویر",
            "alignmentsDropDownLeft": "تراز چپ",
            "alignmentsDropDownCenter": "مرکز هماهنگی",
            "alignmentsDropDownRight": "راست راست کن",
            "alignmentsDropDownJustify": "تراز کردن",
            "imageDisplayDropDownInline": "درون خطی",
            "imageDisplayDropDownBreak": "زنگ تفريح",
            "tableInsertRowDropDownBefore": "قبل از وارد کردن ردیف",
            "tableInsertRowDropDownAfter": "ردیف بعد را وارد کنید",
            "tableInsertRowDropDownDelete": "حذف ردیف",
            "tableInsertColumnDropDownLeft": "درج ستون سمت چپ",
            "tableInsertColumnDropDownRight": "ستون راست را وارد کنید",
            "tableInsertColumnDropDownDelete": "حذف ستون",
            "tableVerticalAlignDropDownTop": "بالا رفتن",
            "tableVerticalAlignDropDownMiddle": "مطابقت میانه",
            "tableVerticalAlignDropDownBottom": "پایین تر کردن",
            "tableStylesDropDownDashedBorder": "مرز خرد شده",
            "tableStylesDropDownAlternateRows": "ردیفهای متناوب",
            "pasteFormat": "قالب چسباندن",
            "pasteFormatContent": "عمل قالب بندی را انتخاب کنید",
            "plainText": "متن ساده",
            "cleanFormat": "تمیز",
            "keepFormat": "نگاه داشتن"
        },
        "colorpicker": {
            "Apply": "درخواست دادن",
            "Cancel": "لغو",
            "ModeSwitcher": "حالت سوئیچ"
        },
        "uploader": {
            "Browse": "مرور کردن...",
            "Clear": "پاک کردن",
            "Upload": "بارگذاری",
            "dropFilesHint": "یا فایلها را اینجا بگذارید",
            "invalidMaxFileSize": "اندازه فایل خیلی بزرگ است",
            "invalidMinFileSize": "اندازه فایل خیلی کوچک است",
            "invalidFileType": "نوع فایل مجاز نیست",
            "uploadFailedMessage": "فایل آپلود نشد",
            "uploadSuccessMessage": "فایل با موفقیت آپلود شد",
            "removedSuccessMessage": "پرونده با موفقیت حذف شد",
            "removedFailedMessage": "فایل حذف نشد",
            "inProgress": "آپلود",
            "readyToUploadMessage": "آماده برای آپلود",
            "abort": "قطع شدن",
            "remove": "برداشتن",
            "cancel": "لغو",
            "delete": "حذف فایل",
            "pauseUpload": "آپلود فایل متوقف شد",
            "pause": "مکث",
            "resume": "خلاصه",
            "retry": "دوباره امتحان کنید",
            "fileUploadCancel": "آپلود فایل لغو شد"
        },
        "numerictextbox": {
            "incrementTitle": "ارزش افزوده",
            "decrementTitle": "ارزش تخریب"
        },
        "slider": {
            "Increase": "افزایش دادن",
            "Decrease": "نزول کردن"
        },
        "treegrid": {
            "Above": "در بالا",
            "Below": "در زیر",
            "AddRow": "اضافه کردن ردیف",
            "ExpandAll": "گسترش همه",
            "CollapseAll": "سقوط همه"
        },
        "schedule": {
            "day": "روز",
            "week": "هفته",
            "workWeek": "هفته کاری",
            "month": "ماه",
            "agenda": "دستور جلسه",
            "weekAgenda": "هفته برنامه",
            "workWeekAgenda": "برنامه کاری هفته",
            "monthAgenda": "برنامه ماه",
            "today": "امروز",
            "noEvents": "هیچ رویدادی وجود ندارد",
            "emptyContainer": "هیچ رویدادی در این روز برنامه ریزی نشده است.",
            "allDay": "تمام روز",
            "start": "شروع کنید",
            "end": "پایان",
            "more": "بیشتر",
            "close": "نزدیک",
            "cancel": "لغو",
            "noTitle": "(بدون عنوان)",
            "delete": "حذف",
            "deleteEvent": "حذف رویداد",
            "deleteMultipleEvent": "حذف رویدادهای متعدد",
            "selectedItems": "آیتم های انتخاب شده",
            "deleteSeries": "حذف سری",
            "edit": "ویرایش کنید",
            "editSeries": "ویرایش سری",
            "editEvent": "ویرایش رویداد",
            "createEvent": "ايجاد كردن",
            "subject": "موضوع",
            "addTitle": "عنوان اضافه کن",
            "moreDetails": "جزئیات بیشتر",
            "save": "صرفه جویی",
            "editContent": "آیا میخواهید فقط این رویداد یا مجموعه کامل را ویرایش کنید؟",
            "deleteRecurrenceContent": "آیا می خواهید تنها این رویداد یا مجموعه کامل را حذف کنید؟",
            "deleteContent": "آیا شما مطمئن هستید که میخواهید این رویداد را حذف کنید؟",
            "deleteMultipleContent": "آیا مطمئن هستید که می خواهید رویدادهای انتخاب شده را حذف کنید؟",
            "newEvent": "رویداد جدید",
            "title": "عنوان",
            "location": "محل",
            "description": "شرح",
            "timezone": "منطقه زمانی",
            "startTimezone": "شروع منطقه زمانی",
            "endTimezone": "پایان منطقه زمانی",
            "repeat": "تکرار",
            "saveButton": "صرفه جویی",
            "cancelButton": "لغو",
            "deleteButton": "حذف",
            "recurrence": "عود",
            "wrongPattern": "الگوی تکرار معتبر نیست",
            "seriesChangeAlert": "تغییرات به موارد خاص این مجموعه لغو خواهد شد و آن رویدادها دوباره به مجموعه خواهد رسید.",
            "createError": "مدت زمان این رویداد باید کوتاهتر از حد مجاز آن باشد. طول مدت را کوتاه کنید یا الگوی عود در ویرایشگر رویداد عود را تغییر دهید.",
            "recurrenceDateValidation": "چند ماه کمتر از تاریخ انتخاب شده است. برای این ماه، وقوع به آخرین تاریخ ماه می رسد.",
            "sameDayAlert": "دو رویداد از یک رویداد مشابه در همان روز رخ نمی دهد.",
            "editRecurrence": "عود مجدد",
            "repeats": "تکرار می شود",
            "alert": "هشدار",
            "startEndError": "تاریخ پایان انتخاب قبل از تاریخ شروع می شود.",
            "invalidDateError": "مقدار تاریخ ورودی نامعتبر است",
            "ok": "خوب",
            "occurrence": "رخداد",
            "series": "سلسله",
            "previous": "قبلی",
            "next": "بعد",
            "timelineDay": "روز گاهشمار",
            "timelineWeek": "هفته گاهشمار",
            "timelineWorkWeek": "هفته کاری Timeline",
            "timelineMonth": "ماه گاهشمار"
        },
        "recurrenceeditor": {
            "none": "هیچ یک",
            "daily": "روزانه",
            "weekly": "هفتگی",
            "monthly": "ماهانه",
            "month": "ماه",
            "yearly": "سالانه",
            "never": "هرگز",
            "until": "تا زمان",
            "count": "شمردن",
            "first": "اولین",
            "second": "دومین",
            "third": "سوم",
            "fourth": "چهارم",
            "last": "آخر",
            "repeat": "تکرار",
            "repeatEvery": "تکرار هر",
            "on": "تکرار در",
            "end": "پایان",
            "onDay": "روز",
            "days": "روزها)",
            "weeks": "هفته (ها)",
            "months": "ماه ها)",
            "years": "سال ها)",
            "every": "هرکدام",
            "summaryTimes": "بار)",
            "summaryOn": "بر",
            "summaryUntil": "تا زمان",
            "summaryRepeat": "تکرار می شود",
            "summaryDay": "روزها)",
            "summaryWeek": "هفته (ها)",
            "summaryMonth": "ماه ها)",
            "summaryYear": "سال ها)",
            "monthWeek": "هفته ماه",
            "monthPosition": "موقعیت ماه",
            "monthExpander": "ماه گسترش",
            "yearExpander": "Expander سال",
            "repeatInterval": "تکرار فاصله"
        },
        "pdfviewer": {
            "PdfViewer": "مشاهدهگر PDF",
            "Cancel": "لغو",
            "Download file": "دریافت فایل",
            "Download": "دانلود",
            "Enter Password": "این سند با رمز محافظت شده است. لطفا یک رمز عبور وارد کنید",
            "File Corrupted": "فایل خراب شده",
            "File Corrupted Content": "پرونده خراب شده است و نمی تواند باز شود",
            "Fit Page": "متناسب با صفحه",
            "Fit Width": "عرض متناسب",
            "Automatic": "خودکار",
            "Go To First Page": "نمایش صفحه اول",
            "Invalid Password": "رمز نادرست لطفا دوباره تلاش کنید.",
            "Next Page": "نمایش صفحه بعدی",
            "OK": "خوب",
            "Open": "فایل را باز کنید",
            "Page Number": "شماره صفحه فعلی",
            "Previous Page": "نمایش صفحه قبلی",
            "Go To Last Page": "نمایش آخرین صفحه",
            "Zoom": "بزرگنمایی",
            "Zoom In": "بزرگنمایی",
            "Zoom Out": "کوچک نمایی",
            "Page Thumbnails": "ریز عکسها",
            "Bookmarks": "نشانکها",
            "Print": "فایل چاپ",
            "Password Protected": "رمز عبور مورد نیاز است",
            "Copy": "کپی کنید",
            "Text Selection": "ابزار انتخاب متن",
            "Panning": "حالت پان",
            "Text Search": "متن را پیدا کنید",
            "Find in document": "در سند پیدا کنید",
            "Match case": "مسابقه مورد",
            "Apply": "درخواست دادن",
            "GoToPage": "برو به صفحه",
            "No matches": "بیننده جستجوی سند را به پایان رسانده است. مسابقات بیشتر یافت نشد",
            "No Text Found": "بدون متن یافت نشد",
            "Server error": "سرویس وب گوش نمی دهد PDF Viewer بستگی به سرویس وب برای تمام ویژگی های آن دارد. لطفا خدمات وب را برای ادامه ادامه دهید"
        },
        "pivotview": {
            "grandTotal": "مجموع کل",
            "total": "جمع",
            "value": "ارزش",
            "noValue": "ارزش ندارد",
            "row": "ردیف",
            "column": "ستون",
            "collapse": "سقوط - فروپاشی",
            "expand": "بسط دادن",
            "rowAxisPrompt": "ردیف قطره اینجا",
            "columnAxisPrompt": "ستون قطره اینجا",
            "valueAxisPrompt": "مقدار افت در اینجا",
            "filterAxisPrompt": "قطره فیلتر اینجا",
            "filter": "فیلتر کردن",
            "filtered": "فیلتر شده",
            "sort": "مرتب سازی",
            "filters": "فیلترها",
            "rows": "ردیفها",
            "columns": "ستون ها",
            "values": "ارزش های",
            "close": "نزدیک",
            "cancel": "لغو",
            "delete": "حذف",
            "calculatedField": "فیلد محاسبه شده",
            "createCalculatedField": "ایجاد زمینه محاسبه",
            "fieldName": "نام فیلد را وارد کنید",
            "error": "خطا",
            "invalidFormula": "نام یا فرم نامعتبر است",
            "dropText": "مثال: (Sum (Order_Count) + 'Sum (In_Stock)') * 250",
            "dropTextMobile": "اضافه کردن فیلدها و ویرایش فرمول اینجا.",
            "dropAction": "محدوده محاسبه نمیتواند در هر منطقه دیگری جز محدوده ارزش قرار گیرد.",
            "alert": "هشدار",
            "warning": "اخطار",
            "ok": "خوب",
            "search": "جستجو کردن",
            "drag": "کشیدن",
            "remove": "برداشتن",
            "sum": "مجموع",
            "average": "میانگین",
            "count": "شمردن",
            "min": "حداقل",
            "max": "حداکثر",
            "allFields": "تمام زمینه ها",
            "formula": "فرمول",
            "addToRow": "اضافه کردن به ردیف",
            "addToColumn": "اضافه کردن به ستون",
            "addToValue": "اضافه کردن به ارزش",
            "addToFilter": "اضافه کردن به فیلتر",
            "emptyData": "هیچ پرونده برای نمایش نیست",
            "fieldExist": "یک فیلد در این نام وجود دارد. لطفا نام دیگری را وارد کنید",
            "confirmText": "یک فیلد محاسبه قبلا در این نام وجود دارد. آیا می خواهی جایگزین کنی؟",
            "noMatches": "هیچ بازی",
            "format": "مقادیر خلاصه توسط",
            "edit": "ویرایش کنید",
            "clear": "پاک کردن",
            "formulaField": "کشیدن و رها کردن فیلدها به فرمول",
            "dragField": "فیلد را به فرمول بکشید",
            "clearFilter": "پاک کردن",
            "by": "توسط",
            "enterValue": "ارزش را وارد کنید",
            "chooseDate": "تاریخ را وارد کنید",
            "Equals": "برابر است",
            "DoesNotEquals": "مساوی نیست",
            "BeginWith": "شروع با",
            "DoesNotBeginWith": "با شروع نمی شود",
            "EndsWith": "به پایان می رسد با",
            "DoesNotEndsWith": "پایان نمی دهد",
            "Contains": "شامل",
            "DoesNotContains": "شامل نمی شود",
            "GreaterThan": "بزرگتر از",
            "GreaterThanOrEqualTo": "بزرگتر یا مساوی با",
            "LessThan": "کمتر از",
            "LessThanOrEqualTo": "کمتر از یا برابر به",
            "Between": "بین",
            "NotBetween": "نه بین",
            "Before": "قبل از",
            "BeforeOrEqualTo": "قبل و یا برابر به",
            "After": "بعد از",
            "AfterOrEqualTo": "پس از آن یا برابر",
            "member": "عضو",
            "label": "برچسب",
            "date": "تاریخ",
            "labelTextContent": "مواردی را که برچسب را نمایش می دهد را نمایش دهید",
            "dateTextContent": "مواردی را که تاریخ آن را نمایش می دهد را نمایش دهید",
            "valueTextContent": "مواردی را برای آن نمایش دهید",
            "And": "و",
            "conditionalFormating": "قالب بندی شرطی",
            "apply": "درخواست دادن",
            "condition": "اضافه کردن شرط",
            "formatLabel": "فرمت"
        },
        "pivotfieldlist": {
            "staticFieldList": "فهرست فیلد محوری",
            "fieldList": "فهرست فیلد",
            "dropFilterPrompt": "قطره فیلتر اینجا",
            "dropColPrompt": "ستون قطره اینجا",
            "dropRowPrompt": "ردیف قطره اینجا",
            "dropValPrompt": "مقدار افت در اینجا",
            "addPrompt": "فیلد را اینجا اضافه کنید",
            "adaptiveFieldHeader": "فیلد را انتخاب کنید",
            "centerHeader": "زمینه های بین محورهای زیر را بکشید:",
            "add": "اضافه کردن",
            "drag": "کشیدن",
            "filter": "فیلتر کردن",
            "filtered": "فیلتر شده",
            "sort": "مرتب سازی",
            "remove": "برداشتن",
            "filters": "فیلترها",
            "rows": "ردیفها",
            "columns": "ستون ها",
            "values": "ارزش های",
            "calculatedField": "فیلد محاسبه شده",
            "createCalculatedField": "ایجاد زمینه محاسبه",
            "fieldName": "نام فیلد را وارد کنید",
            "error": "خطا",
            "invalidFormula": "نام یا فرم نامعتبر است",
            "dropText": "مثال: (Sum (Order_Count) + 'Sum (In_Stock)') * 250",
            "dropTextMobile": "اضافه کردن فیلدها و ویرایش فرمول اینجا.",
            "dropAction": "محدوده محاسبه نمیتواند در هر منطقه دیگری جز محدوده ارزش قرار گیرد.",
            "search": "جستجو کردن",
            "close": "نزدیک",
            "cancel": "لغو",
            "delete": "حذف",
            "alert": "هشدار",
            "warning": "اخطار",
            "ok": "خوب",
            "sum": "مجموع",
            "average": "میانگین",
            "count": "شمردن",
            "min": "حداقل",
            "max": "حداکثر",
            "allFields": "تمام زمینه ها",
            "formula": "فرمول",
            "fieldExist": "یک فیلد در این نام وجود دارد. لطفا نام دیگری را وارد کنید",
            "confirmText": "یک فیلد محاسبه قبلا در این نام وجود دارد. آیا می خواهی جایگزین کنی؟",
            "noMatches": "هیچ بازی",
            "format": "مقادیر خلاصه توسط",
            "edit": "ویرایش کنید",
            "clear": "پاک کردن",
            "formulaField": "کشیدن و رها کردن فیلدها به فرمول",
            "dragField": "فیلد را به فرمول بکشید",
            "clearFilter": "پاک کردن",
            "by": "توسط",
            "enterValue": "ارزش را وارد کنید",
            "chooseDate": "تاریخ را وارد کنید",
            "Equals": "برابر است",
            "DoesNotEquals": "مساوی نیست",
            "BeginWith": "شروع با",
            "DoesNotBeginWith": "با شروع نمی شود",
            "EndsWith": "به پایان می رسد با",
            "DoesNotEndsWith": "پایان نمی دهد",
            "Contains": "شامل",
            "DoesNotContains": "شامل نمی شود",
            "GreaterThan": "بزرگتر از",
            "GreaterThanOrEqualTo": "بزرگتر یا مساوی با",
            "LessThan": "کمتر از",
            "LessThanOrEqualTo": "کمتر از یا برابر به",
            "Between": "بین",
            "NotBetween": "نه بین",
            "Before": "قبل از",
            "BeforeOrEqualTo": "قبل و یا برابر به",
            "After": "بعد از",
            "AfterOrEqualTo": "پس از آن یا برابر",
            "member": "عضو",
            "label": "برچسب",
            "date": "تاریخ",
            "value": "ارزش",
            "labelTextContent": "مواردی را که برچسب را نمایش می دهد را نمایش دهید",
            "dateTextContent": "مواردی را که تاریخ آن را نمایش می دهد را نمایش دهید",
            "valueTextContent": "مواردی را برای آن نمایش دهید",
            "And": "و",
            "apply": "درخواست دادن"
        },
        "diagram": {
            "Copy": "کپی کنید",
            "Cut": "برش",
            "Paste": "چسباندن",
            "Undo": "لغو",
            "Redo": "دوباره بکش",
            "SelectAll": "انتخاب همه",
            "Grouping": "گروه بندی",
            "Group": "گروه",
            "UnGroup": "یون گروه",
            "Order": "سفارش",
            "BringToFront": "به جلو بروید",
            "MoveForward": "به جلو حرکت کن",
            "SendToBack": "ارسال به پشت",
            "SendBackward": "بازگشت به عقب"
        },
        "inplaceeditor": {
            "save": "صرفه جویی",
            "cancel": "لغو",
            "editIcon": "کلیک کنید تا ویرایش شود",
            "editAreaClick": "کلیک کنید تا ویرایش شود",
            "editAreaDoubleClick": "دوبار کلیک کنید تا ویرایش شود"
        },
        "dropdowns": {
            "noRecordsTemplate": "هیچ اسنادی یافت نشد",
            "actionFailureTemplate": "درخواست شکست خورد",
            "overflowCountTemplate": "+ $ {شمارش} بیشتر ..",
            "selectAllText": "انتخاب همه",
            "unSelectAllText": "لغو انتخاب همه",
            "totalCountTemplate": "$ {count} انتخاب شده است"
        },
        "drop-down-list": {
            "noRecordsTemplate": "هیچ اسنادی یافت نشد",
            "actionFailureTemplate": "درخواست شکست خورد"
        },
        "combo-box": {
            "noRecordsTemplate": "هیچ اسنادی یافت نشد",
            "actionFailureTemplate": "درخواست شکست خورد"
        },
        "auto-complete": {
            "noRecordsTemplate": "هیچ اسنادی یافت نشد",
            "actionFailureTemplate": "درخواست شکست خورد"
        },
        "multi-select": {
            "noRecordsTemplate": "هیچ اسنادی یافت نشد",
            "actionFailureTemplate": "درخواست شکست خورد",
            "overflowCountTemplate": "+ $ {شمارش} بیشتر ..",
            "selectAllText": "انتخاب همه",
            "unSelectAllText": "لغو انتخاب همه"
        },
        "listbox": {
            "noRecordsTemplate": "هیچ اسنادی یافت نشد",
            "actionFailureTemplate": "درخواست شکست خورد",
            "selectAllText": "انتخاب همه",
            "unSelectAllText": "لغو انتخاب همه",
            "moveUp": "حرکت کن",
            "moveDown": "حرکت به پایین",
            "moveTo": "حرکت به",
            "moveFrom": "حرکت از",
            "moveAllTo": "حرکت به همه",
            "moveAllFrom": "حرکت همه از"
        },
        "gantt": {
            "emptyRecord": "هیچ پرونده برای نمایش نیست",
            "id": "شناسه",
            "name": "نام",
            "startDate": "تاریخ شروع",
            "endDate": "تاریخ پایان",
            "duration": "مدت زمان",
            "progress": "پیش رفتن",
            "dependency": "وابستگی",
            "notes": "یادداشت",
            "baselineStartDate": "تاریخ شروع پایه",
            "baselineEndDate": "تاریخ پایان پایه",
            "type": "تایپ کنید",
            "offset": "انحراف",
            "resourceName": "منابع",
            "resourceID": "شناسه منبع",
            "day": "روز",
            "hour": "ساعت",
            "minute": "دقیقه",
            "days": "روزها",
            "hours": "ساعت ها",
            "minutes": "دقایق",
            "generalTab": "عمومی",
            "customTab": "ستون های سفارشی",
            "writeNotes": "یادداشت کنید",
            "addDialogTitle": "وظیفه جدید",
            "editDialogTitle": "اطلاعات کار",
            "saveButton": "صرفه جویی",
            "add": "اضافه کردن",
            "edit": "ویرایش کنید",
            "update": "به روز رسانی",
            "delete": "حذف",
            "cancel": "لغو",
            "search": "جستجو کردن",
            "addTask": "اضافه کردن کار",
            "editTask": "ویرایش وظیفه",
            "deleteTask": "حذف وظیفه",
            "expandAllTasks": "گسترش تمام وظایف",
            "collapseAllTasks": "سقوط تمام وظایف",
            "expandAll": "گسترش همه",
            "collapseAll": "سقوط همه",
            "nextTimeSpan": "بارگذاری بعدی",
            "prevTimeSpan": "زمان بار قبلی",
            "okText": "خوب",
            "confirmDelete": "آیا مطمئن هستید که میخواهید رکورد را حذف کنید؟",
            "from": "از جانب",
            "to": "به",
            "taskLink": "لینک کار",
            "lag": "تاخیر",
            "start": "شروع کنید",
            "finish": "پایان دادن",
            "enterValue": "مقدار را وارد کنید",
            "taskBeforePredecessor_FS": "شما {0} حرکت کردید تا قبل از شروع {1} 'پایان یابد و دو وظیفه مرتبط هستند. به عنوان نتیجه، پیوندهای قابل احترام نیست. یک عمل زیر را برای انجام انتخاب کنید",
            "taskAfterPredecessor_FS": "شما {0} را از «{1}» منتقل کردید و دو وظیفه مرتبط هستند. به عنوان نتیجه، پیوندهای قابل احترام نیست. یک عمل زیر را برای انجام انتخاب کنید",
            "taskBeforePredecessor_SS": "شما '{0}' حرکت کردید تا قبل از شروع {1} شروع شود و دو وظیفه مرتبط هستند. به عنوان نتیجه، پیوندهای قابل احترام نیست. یک عمل زیر را برای انجام انتخاب کنید",
            "taskAfterPredecessor_SS": "شما {0} حرکت کردید تا پس از شروع {1} شروع شود و دو وظیفه مرتبط هستند. به عنوان نتیجه، پیوندهای قابل احترام نیست. یک عمل زیر را برای انجام انتخاب کنید",
            "taskBeforePredecessor_FF": "شما '{0}' را به پایان رساندید تا قبل از {1} 'پایان یابد و دو وظیفه مرتبط هستند. به عنوان نتیجه، پیوندهای قابل احترام نیست. یک عمل زیر را برای انجام انتخاب کنید",
            "taskAfterPredecessor_FF": "شما {0} حرکت کردید تا پس از پایان {1} 'پایان یابد و دو وظیفه مرتبط هستند. به عنوان نتیجه، پیوندهای قابل احترام نیست. یک عمل زیر را برای انجام انتخاب کنید",
            "taskBeforePredecessor_SF": "شما {0} را از «{1}» به شروع می کنید و دو وظیفه مرتبط هستند. به عنوان نتیجه، پیوندهای قابل احترام نیست. یک عمل زیر را برای انجام انتخاب کنید",
            "taskAfterPredecessor_SF": "شما {0} حرکت کردید تا بعد از {1} شروع کنید و دو وظیفه مرتبط هستند. به عنوان نتیجه، پیوندهای قابل احترام نیست. یک عمل زیر را برای انجام انتخاب کنید"
        },
        "dialog": {
            "close": "نزدیک"
        },
        "rich-text-editor": {
            "alignments": "ترازوها",
            "justifyleft": "justifyLeft",
            "justifycenter": "توجیه مرکز",
            "justifyright": "توجیه کنید",
            "justifyfull": "توجیه کامل",
            "fontname": "fontName",
            "fontsize": "اندازه فونت",
            "fontcolor": "fontColor",
            "backgroundcolor": "رنگ پس زمینه",
            "clearformat": "ClearFormat",
            "clearall": "همه را پاک کن",
            "unorderedlist": "لیست نامرتب",
            "orderedlist": "فهرست مرتبشده",
            "createlink": "createLink",
            "openlink": "لینک های باز",
            "editlink": "ویرایش لینک",
            "removelink": "حذف لینک",
            "openimagelink": "لینک های باز",
            "editimagelink": "ویرایش لینک",
            "removeimagelink": "حذف لینک",
            "image": "تصویر",
            "replace": "جایگزین کردن",
            "align": "تراز کردن",
            "caption": "عنوان",
            "remove": "برداشتن",
            "insertlink": "وارد کردن لینک",
            "display": "نمایش دادن",
            "alttext": "متن جایگزین",
            "dimension": "بعد، ابعاد، اندازه",
            "fullscreen": "تمام صفحه",
            "maximize": "به حداکثر رساندن",
            "minimize": "به حداقل رساندن",
            "lowercase": "lowercase",
            "uppercase": "مقیاس بزرگ",
            "print": "چاپ",
            "formats": "فرمت ها",
            "sourcecode": "sourcecode",
            "preview": "پیش نمایش",
            "viewside": "دیدگاه",
            "insertcode": "کد را وارد کنید",
            "justifyLeft": "تراز چپ",
            "justifyCenter": "مرکز هماهنگی",
            "justifyRight": "راست راست کن",
            "justifyFull": "تراز کردن",
            "fontName": "نام فونت",
            "fontSize": "اندازه فونت",
            "fontColor": "رنگ فونت",
            "backgroundColor": "رنگ پس زمینه",
            "bold": "جسورانه",
            "italic": "کتانی",
            "underline": "برجسته کردن",
            "strikethrough": "از بین بردن",
            "cut": "برش",
            "copy": "کپی کنید",
            "paste": "چسباندن",
            "indent": "عقب نشینی",
            "outdent": "بی نظیر",
            "undo": "لغو کردن",
            "redo": "مجدد",
            "superscript": "فوق العاده",
            "subscript": "زیرمجموعه",
            "createLink": "درج لینک",
            "openLink": "لینک های باز",
            "editLink": "ویرایش پیوند",
            "removeLink": "پیوند را حذف کنید",
            "insertLink": "لینک را وارد کنید",
            "altText": "متن جایگزین",
            "lowerCase": "مورد پایینتر",
            "upperCase": "مورد بالا",
            "insertCode": "کد را وارد کنید",
            "linkText": "نمایش متن",
            "linkTooltipLabel": "راهنمایی",
            "linkWebUrl": "آدرس وب",
            "linkurl": "http://example.com",
            "linkOpenInNewWindow": "لینک را در پنجره جدید باز کنید",
            "linkHeader": "لینک را وارد کنید",
            "dialogInsert": "قرار دادن",
            "dialogCancel": "لغو",
            "dialogUpdate": "به روز رسانی",
            "imageHeader": "درج تصویر",
            "imageLinkHeader": "شما همچنین می توانید یک لینک از وب فراهم کنید",
            "mdimageLink": "لطفا برای تصویر خود یک URL بگذارید",
            "imageUploadMessage": "قطره عکس اینجا و یا فهرست برای آپلود",
            "imageDeviceUploadMessage": "برای آپلود اینجا کلیک کنید",
            "imageAlternateText": "متن جایگزین",
            "alternateHeader": "متن جایگزین",
            "browse": "مرور کردن",
            "imageUrl": "http://example.com/image.png",
            "imageCaption": "عنوان",
            "imageSizeHeader": "اندازه تصویر",
            "imageHeight": "ارتفاع",
            "imageWidth": "عرض",
            "textPlaceholder": "متن را وارد کنید"
        },
        "inplace-editor": {
            "editIcon": "کلیک کنید تا ویرایش شود",
            "save": "صرفه جویی",
            "cancel": "لغو"
        },
        "chart": {
            "Zoom": "بزرگنمایی",
            "ZoomIn": "بزرگنمایی",
            "ZoomOut": "کوچک نمایی",
            "Reset": "تنظیم مجدد",
            "Pan": "ماهی تابه",
            "ResetZoom": "تنظیم مجدد زوم"
        },
        "drop-down-base": {
            "noRecordsTemplate": "هیچ اسنادی یافت نشد",
            "actionFailureTemplate": "درخواست شکست خورد"
        },
        "maps": {
            "Zoom": "بزرگنمایی",
            "ZoomIn": "بزرگنمایی",
            "ZoomOut": "کوچک نمایی",
            "Reset": "تنظیم مجدد",
            "Pan": "ماهی تابه",
            "ResetZoom": "تنظیم مجدد زوم"
        }
    }
}