{
    "ms": {
        "chart": {
            "Zoom": "Zum",
            "ZoomIn": "Mengezum masuk",
            "ZoomOut": "Zum keluar",
            "Reset": "Tetapkan semula",
            "Pan": "Pan",
            "ResetZoom": "Tetapkan semula Zum"
        },
        "DocumentEditor": {
            "Table": "Jadual",
            "Row": "Row",
            "Cell": "Sel",
            "Ok": "Okey",
            "Cancel": "Batalkan",
            "Size": "Saiz",
            "Preferred Width": "Lebar pilihan",
            "Points": "Mata",
            "Percent": "Peratus",
            "Measure in": "Ukur masuk",
            "Alignment": "Penjajaran",
            "Left": "Ditinggalkan",
            "Center": "Pusat",
            "Right": "Betul",
            "Justify": "Justify",
            "Indent from left": "Inden dari kiri",
            "Borders and Shading": "Borders dan Shading",
            "Options": "Pilihan",
            "Specify height": "Tentukan ketinggian",
            "At least": "Sekurang-kurangnya",
            "Exactly": "Betul",
            "Row height is": "Ketinggian baris adalah",
            "Allow row to break across pages": "Benarkan baris untuk memecah halaman",
            "Repeat as header row at the top of each page": "Ulangi sebagai baris tajuk di bahagian atas setiap halaman",
            "Vertical alignment": "Penjajaran menegak",
            "Top": "Teratas",
            "Bottom": "Bawah",
            "Default cell margins": "Margin sel default",
            "Default cell spacing": "Jarak sel lalai",
            "Allow spacing between cells": "Benarkan jarak antara sel-sel",
            "Cell margins": "Margin sel",
            "Same as the whole table": "Sama seperti keseluruhan jadual",
            "Borders": "Sempadan",
            "None": "Tiada",
            "Single": "Single",
            "Dot": "Dot",
            "DashSmallGap": "DashSmallGap",
            "DashLargeGap": "DashLargeGap",
            "DashDot": "DashDot",
            "DashDotDot": "DashDotDot",
            "Double": "Double",
            "Triple": "Triple",
            "ThinThickSmallGap": "ThinThickSmallGap",
            "ThickThinSmallGap": "ThickThinSmallGap",
            "ThinThickThinSmallGap": "ThinThickThinSmallGap",
            "ThinThickMediumGap": "ThinThickMediumGap",
            "ThickThinMediumGap": "ThickThinMediumGap",
            "ThinThickThinMediumGap": "ThinThickThinMediumGap",
            "ThinThickLargeGap": "ThinThickLargeGap",
            "ThickThinLargeGap": "ThickThinLargeGap",
            "ThinThickThinLargeGap": "ThinThickThinLargeGap",
            "SingleWavy": "SingleWavy",
            "DoubleWavy": "DoubleWavy",
            "DashDotStroked": "DashDotStroked",
            "Emboss3D": "Emboss3D",
            "Engrave3D": "Engrave3D",
            "Outset": "Awal",
            "Inset": "Inset",
            "Thick": "Tebal",
            "Style": "Gaya",
            "Width": "Lebar",
            "Height": "Ketinggian",
            "Letter": "Surat",
            "Tabloid": "Tabloid",
            "Legal": "Undang-undang",
            "Statement": "Kenyataan",
            "Executive": "Eksekutif",
            "A3": "A3",
            "A4": "A4",
            "A5": "A5",
            "B4": "B4",
            "B5": "B5",
            "Custom Size": "Saiz tersuai",
            "Different odd and even": "Ganjil yang berbeza dan juga",
            "Different first page": "Halaman pertama yang berbeza",
            "From edge": "Dari tepi",
            "Header": "Kepala",
            "Footer": "Footer",
            "Margin": "Margin",
            "Paper": "Kertas",
            "Layout": "Susun atur",
            "Orientation": "Orientasi",
            "Landscape": "Landskap",
            "Portrait": "Potret",
            "Table Of Contents": "Isi kandungan",
            "Show page numbers": "Tunjukkan nombor halaman",
            "Right align page numbers": "Nombor halaman penjajaran kanan",
            "Nothing": "Tiada apa-apa",
            "Tab leader": "Ketua tab",
            "Show levels": "Tunjukkan tahap",
            "Use hyperlinks instead of page numbers": "Gunakan hyperlink bukan nombor halaman",
            "Build table of contents from": "Bina jadual kandungan dari",
            "Styles": "Gaya",
            "Available styles": "Gaya yang ada",
            "TOC level": "Tahap TOC",
            "Heading": "Tajuk",
            "List Paragraph": "Senaraikan Perenggan",
            "Normal": "Normal",
            "Outline levels": "Tahap garis",
            "Table entry fields": "Jadual kemasukan jadual",
            "Modify": "Ubah suai",
            "Color": "Warna",
            "Setting": "Menetapkan",
            "Box": "Kotak",
            "All": "Semua",
            "Custom": "Custom",
            "Preview": "Pratonton",
            "Shading": "Shading",
            "Fill": "Isi",
            "Apply To": "Memohon kepada",
            "Table Properties": "Harta Jadual",
            "Cell Options": "Pilihan Sel",
            "Table Options": "Pilihan Jadual",
            "Insert Table": "Masukkan Jadual",
            "Number of columns": "Bilangan lajur",
            "Number of rows": "Bilangan baris",
            "Text to display": "Teks untuk dipaparkan",
            "Address": "Alamat",
            "Insert Hyperlink": "Masukkan Hyperlink",
            "Edit Hyperlink": "Edit Hyperlink",
            "Insert": "Masukkan",
            "General": "Ketua",
            "Indentation": "Indentasi",
            "Before text": "Sebelum teks",
            "Special": "Khas",
            "First line": "Barisan pertama",
            "Hanging": "Menggantung",
            "After text": "Selepas teks",
            "By": "Oleh",
            "Before": "Sebelum ini",
            "Line Spacing": "Jarak baris",
            "After": "Selepas",
            "At": "Pada",
            "Multiple": "Pelbagai",
            "Spacing": "Jarak",
            "Define new Multilevel list": "Tentukan senarai Multilevel baru",
            "List level": "Tahap senarai",
            "Choose level to modify": "Pilih tahap untuk mengubah suai",
            "Level": "Tahap",
            "Number format": "Format nombor",
            "Number style for this level": "Gaya nombor untuk tahap ini",
            "Enter formatting for number": "Masukkan pemformatan untuk nombor",
            "Start at": "Bermula pada",
            "Restart list after": "Mula semula senarai selepas",
            "Position": "Jawatan",
            "Text indent at": "Teks indent di",
            "Aligned at": "Aligned at",
            "Follow number with": "Ikut nombor dengan",
            "Tab character": "Watak tab",
            "Space": "Ruang",
            "Arabic": "Arab",
            "UpRoman": "UpRoman",
            "LowRoman": "LowRoman",
            "UpLetter": "UpLetter",
            "LowLetter": "LowLetter",
            "Number": "Nombor",
            "Leading zero": "Memimpin sifar",
            "Bullet": "Bullet",
            "Ordinal": "Ordinal",
            "Ordinal Text": "Teks Ordinal",
            "For East": "Untuk Timur",
            "No Restart": "Tidak dimulakan semula",
            "Font": "Fon",
            "Font style": "Gaya fon",
            "Underline style": "Gaya bawah garis",
            "Font color": "Warna fon",
            "Effects": "Kesan",
            "Strikethrough": "Strikethrough",
            "Superscript": "Superskrip",
            "Subscript": "Subskrip",
            "Double strikethrough": "Penyerang berganda",
            "Regular": "Biasa",
            "Bold": "Bold",
            "Italic": "Italic",
            "Cut": "Potong",
            "Copy": "Salinan",
            "Paste": "Tampal",
            "Hyperlink": "Hyperlink",
            "Open Hyperlink": "Buka Hyperlink",
            "Copy Hyperlink": "Salin Hyperlink",
            "Remove Hyperlink": "Keluarkan Hyperlink",
            "Paragraph": "Perenggan",
            "Merge Cells": "Mencantumkan sel",
            "Insert Above": "Masukkan Atas",
            "Insert Below": "Masukkan di bawah",
            "Insert Left": "Masukkan Kiri",
            "Insert Right": "Masukkan Hak",
            "Delete": "Padam",
            "Delete Table": "Padamkan Jadual",
            "Delete Row": "Padamkan Row",
            "Delete Column": "Padamkan Kolom",
            "File Name": "Nama fail",
            "Format Type": "Jenis Format",
            "Save": "Simpan",
            "Navigation": "Navigasi",
            "Results": "Keputusan",
            "Replace": "Ganti",
            "Replace All": "Ganti Semua",
            "We replaced all": "Kami menggantikan semua",
            "Find": "Cari",
            "No matches": "Tiada perlawanan",
            "All Done": "Semua Selesai",
            "Result": "Keputusan",
            "of": "daripada",
            "instances": "contohnya",
            "with": "dengan",
            "Click to follow link": "Klik untuk ikut pautan",
            "Continue Numbering": "Teruskan Penomboran",
            "Bookmark name": "Nama penanda buku",
            "Close": "Tutup",
            "Restart At": "Mulakan Semula Pada",
            "Properties": "Hartanah",
            "Name": "Nama",
            "Style type": "Jenis gaya",
            "Style based on": "Gaya berdasarkan",
            "Style for following paragraph": "Gaya untuk perenggan berikut",
            "Formatting": "Pemformatan",
            "Numbering and Bullets": "Penomboran dan Peluru",
            "Numbering": "Penomboran",
            "Update Field": "Kemas kini Medan",
            "Edit Field": "Edit Medan",
            "Bookmark": "Penanda buku",
            "Page Setup": "Persediaan Halaman",
            "No bookmarks found": "Tiada penanda buku ditemui",
            "Number format tooltip information": "Format nombor peringkat tunggal: </ br> [PREFIX]% [LEVELNUMBER] [SUFFIX] </ br> Sebagai contoh, Bab% 1. akan memaparkan penomboran seperti </ br> Bab 1. Item </ br> Bab 2. Item </ br> ... </ br> Bab N. Item </ br> </ br> Format nombor berganda: </ br > [PREFIX]% [LEVELNUMBER] [SUFFIX] + [PREFIX]% [LEVELNUMBER] [SUFFIX] </ br> Sebagai contoh,% 1.% 2. akan memaparkan penomboran seperti </ br> 1.1. Perkara </ br> 1.2. Perkara </ br> ... </ br> 1.N. Perkara",
            "Format": "Format",
            "Create New Style": "Buat Gaya Baru",
            "Modify Style": "Ubahsuai Gaya",
            "New": "Baru",
            "Bullets": "Peluru",
            "Use bookmarks": "Gunakan penanda buku",
            "Table of Contents": "Isi kandungan"
        },
        "grid": {
            "EmptyRecord": "tiada rekod untuk dipaparkan",
            "True": "benar",
            "False": "salah",
            "InvalidFilterMessage": "Data Penapis Tidak Sah",
            "GroupDropArea": "Seret tajuk lajur di sini untuk menyusun lajurnya",
            "UnGroup": "Klik di sini untuk mengumpul",
            "GroupDisable": "Pengkelasan tidak dilumpuhkan untuk lajur ini",
            "FilterbarTitle": "\"sel bar penapis",
            "EmptyDataSourceError": "DataSource tidak boleh kosong pada beban awal kerana lajur dihasilkan dari dataSource dalam AutoGenerate Column Grid",
            "Add": "Tambah",
            "Edit": "Edit",
            "Cancel": "Batalkan",
            "Update": "Kemas kini",
            "Delete": "Padam",
            "Print": "Cetak",
            "Pdfexport": "Eksport PDF",
            "Excelexport": "Eksport Excel",
            "Wordexport": "Eksport Kata",
            "Csvexport": "Eksport CSV",
            "Search": "Carian",
            "Columnchooser": "Lajur",
            "Save": "Simpan",
            "Item": "item",
            "Items": "barangan",
            "EditOperationAlert": "Tiada rekod yang dipilih untuk operasi edit",
            "DeleteOperationAlert": "Tiada rekod yang dipilih untuk operasi padam",
            "SaveButton": "Simpan",
            "OKButton": "okey",
            "CancelButton": "Batalkan",
            "EditFormTitle": "Maklumat mengenai",
            "AddFormTitle": "Tambah Rekod Baru",
            "BatchSaveConfirm": "Adakah anda pasti mahu menyimpan perubahan?",
            "BatchSaveLostChanges": "Perubahan yang tidak disimpan akan hilang. Adakah anda pasti mahu teruskan?",
            "ConfirmDelete": "Adakah anda pasti mahu Menghapus Rekod?",
            "CancelEdit": "Adakah anda pasti mahu Batalkan perubahan?",
            "ChooseColumns": "Pilih Lajur",
            "SearchColumns": "lajur carian",
            "Matchs": "Tiada Perlawanan Dijumpai",
            "FilterButton": "Penapis",
            "ClearButton": "Jelas",
            "StartsWith": "Bermula dengan",
            "EndsWith": "Berakhir Dengan",
            "Contains": "Mengandungi",
            "Equal": "Sama",
            "NotEqual": "Tidak sama",
            "LessThan": "Kurang daripada",
            "LessThanOrEqual": "Kurang Daripada Atau Sama",
            "GreaterThan": "Lebih besar daripada",
            "GreaterThanOrEqual": "Lebih Daripada Atau Sama",
            "ChooseDate": "Pilih Tarikh",
            "EnterValue": "Masukkan nilai",
            "Copy": "Salinan",
            "Group": "Kumpulan mengikut lajur ini",
            "Ungroup": "Ungroup mengikut lajur ini",
            "autoFitAll": "Auto Fit semua lajur",
            "autoFit": "Pasangkan Auto lajur ini",
            "Export": "Eksport",
            "FirstPage": "Muka surat pertama",
            "LastPage": "Muka surat terakhir",
            "PreviousPage": "Halaman sebelumnya",
            "NextPage": "Muka surat seterusnya",
            "SortAscending": "Isih Menaik",
            "SortDescending": "Isih Menurun",
            "EditRecord": "Edit Rekod",
            "DeleteRecord": "Padam Rekod",
            "FilterMenu": "Penapis",
            "SelectAll": "Pilih semua",
            "Blanks": "Kosong",
            "FilterTrue": "Benar",
            "FilterFalse": "Salah",
            "NoResult": "Tiada Perlawanan Dijumpai",
            "ClearFilter": "Kosongkan Penapis",
            "NumberFilter": "Penapis Bilangan",
            "TextFilter": "Penapis Teks",
            "DateFilter": "Penapis Tarikh",
            "DateTimeFilter": "Penapis Tarikh",
            "MatchCase": "Kes pertandingan",
            "Between": "Antara",
            "CustomFilter": "Penapis Tersuai",
            "CustomFilterPlaceHolder": "Masukkan nilai",
            "CustomFilterDatePlaceHolder": "Pilih tarikh",
            "AND": "DAN",
            "OR": "ATAU",
            "ShowRowsWhere": "Tunjukkan baris di mana:"
        },
        "pager": {
            "currentPageInfo": "{0} halaman {1}",
            "totalItemsInfo": "({0} item)",
            "firstPageTooltip": "Pergi ke halaman pertama",
            "lastPageTooltip": "Pergi ke halaman terakhir",
            "nextPageTooltip": "Pergi ke halaman seterusnya",
            "previousPageTooltip": "Pergi ke halaman sebelumnya",
            "nextPagerTooltip": "Pergi ke pager seterusnya",
            "previousPagerTooltip": "Pergi ke pager sebelumnya",
            "pagerDropDown": "Barangan setiap halaman",
            "pagerAllDropDown": "Item",
            "All": "Semua"
        },
        "calendar": {
            "today": "Hari ini"
        },
        "datepicker": {
            "today": "Hari ini",
            "placeholder": "Pilih tarikh"
        },
        "daterangepicker": {
            "placeholder": "Pilih julat tarikh",
            "startLabel": "Tarikh mula",
            "endLabel": "Tarikh tamat",
            "applyText": "Memohon",
            "cancelText": "Batalkan",
            "selectedDays": "Hari Terpilih",
            "days": "Hari",
            "customRange": "Julat Custom"
        },
        "timepicker": {
            "placeholder": "Pilih masa kini"
        },
        "datetimepicker": {
            "today": "Pilih tarikh dan masa",
            "placeholder": "Klik untuk mengedit"
        },
        "inplace-editor": {
            "editIcon": "Simpan",
            "save": "Batalkan",
            "cancel": "Hari"
        },
        "schedule": {
            "day": "Minggu",
            "week": "Minggu Kerja",
            "workWeek": "Bulan",
            "month": "Agenda",
            "agenda": "Agenda Minggu",
            "weekAgenda": "Agenda Minggu Kerja",
            "workWeekAgenda": "Agenda Bulan",
            "monthAgenda": "Hari ini",
            "today": "Tiada acara",
            "noEvents": "Tiada acara yang dijadualkan pada hari ini.",
            "emptyContainer": "Sepanjang hari",
            "allDay": "Mulakan",
            "start": "Akhirnya",
            "end": "lebih lagi",
            "more": "Tutup",
            "close": "Batalkan",
            "cancel": "(Tiada tajuk)",
            "noTitle": "Padam",
            "delete": "Padamkan Peristiwa",
            "deleteEvent": "Padam Pelbagai Acara",
            "deleteMultipleEvent": "Item dipilih",
            "selectedItems": "Padam Siri",
            "deleteSeries": "Edit",
            "edit": "Edit Siri",
            "editSeries": "Edit Acara",
            "editEvent": "Buat",
            "createEvent": "Subjek",
            "subject": "Tambah tajuk",
            "addTitle": "Maklumat lanjut",
            "moreDetails": "Simpan",
            "save": "Adakah anda mahu mengedit sahaja acara atau keseluruhan siri ini?",
            "editContent": "Adakah anda mahu memadamkan acara atau siri keseluruhan ini?",
            "deleteRecurrenceContent": "Adakah anda pasti mahu memadamkan acara ini?",
            "deleteContent": "Adakah anda pasti mahu memadamkan acara yang dipilih?",
            "deleteMultipleContent": "Acara Baru",
            "newEvent": "Tajuk",
            "title": "Lokasi",
            "location": "Penerangan",
            "description": "Zon masa",
            "timezone": "Mulakan Zon Waktu",
            "startTimezone": "Akhir Zon",
            "endTimezone": "Ulang",
            "repeat": "Simpan",
            "saveButton": "Batalkan",
            "cancelButton": "Padam",
            "deleteButton": "Pengulangan",
            "recurrence": "Corak pengulangan tidak sah.",
            "wrongPattern": "Perubahan yang dibuat kepada contoh spesifik dalam siri ini akan dibatalkan dan acara tersebut akan sepadan dengan siri ini lagi.",
            "seriesChangeAlert": "Tempoh acara mestilah lebih pendek daripada berapa kerap berlaku. Mempersendakan tempoh, atau menukar pola berulang dalam editor acara ulangan.",
            "createError": "Beberapa bulan mempunyai kurang daripada tarikh yang dipilih. Untuk bulan-bulan ini, kejadian itu akan jatuh pada tarikh akhir bulan itu.",
            "recurrenceDateValidation": "Dua peristiwa yang sama tidak boleh berlaku pada hari yang sama.",
            "sameDayAlert": "Edit Pengulangan",
            "editRecurrence": "Berulang",
            "repeats": "Amaran",
            "alert": "Tarikh tamat yang dipilih berlaku sebelum tarikh mula.",
            "startEndError": "Nilai tarikh yang dimasukkan adalah tidak sah.",
            "invalidDateError": "Okey",
            "ok": "Kejadian",
            "occurrence": "Siri",
            "series": "Sebelum ini",
            "previous": "Seterusnya",
            "next": "Hari Talian Masa",
            "timelineDay": "Minggu Timeline",
            "timelineWeek": "Minggu Kerja Garis Masa",
            "timelineWorkWeek": "Bulan Timeline",
            "timelineMonth": "Tiada"
        },
        "recurrenceeditor": {
            "none": "Harian",
            "daily": "Setiap minggu",
            "weekly": "Bulanan",
            "monthly": "Bulan",
            "month": "Setiap tahun",
            "yearly": "Jangan sekali-kali",
            "never": "Sehingga",
            "until": "Kira",
            "count": "Pertama",
            "first": "Kedua",
            "second": "Ketiga",
            "third": "Keempat",
            "fourth": "Terakhir",
            "last": "Ulang",
            "repeat": "Ulang setiap",
            "repeatEvery": "Ulang Aktif",
            "on": "Akhirnya",
            "end": "Hari",
            "onDay": "Hari (s)",
            "days": "Minggu (s)",
            "weeks": "Bulan (s)",
            "months": "Tahun (s)",
            "years": "setiap",
            "every": "masa (s)",
            "summaryTimes": "pada",
            "summaryOn": "sehingga",
            "summaryUntil": "Berulang",
            "summaryRepeat": "hari (s)",
            "summaryDay": "minggu (s)",
            "summaryWeek": "bulan (s)",
            "summaryMonth": "tahun (s)",
            "summaryYear": "Minggu Bulan",
            "monthWeek": "Kedudukan Bulan",
            "monthPosition": "Expander Bulan",
            "monthExpander": "Expander Tahun",
            "yearExpander": "Ulang Selang",
            "repeatInterval": "penjajaran"
        },
        "rich-text-editor": {
            "alignments": "justifyLeft",
            "justifyleft": "justifyCenter",
            "justifycenter": "justifyRight",
            "justifyright": "justifyFull",
            "justifyfull": "fontName",
            "fontname": "Saiz huruf",
            "fontsize": "fontColor",
            "fontcolor": "warna latar belakang",
            "backgroundcolor": "clearFormat",
            "clearformat": "kosongkan semua",
            "clearall": "unorderedList",
            "unorderedlist": "perintahList",
            "orderedlist": "createLink",
            "createlink": "openLink",
            "openlink": "editLink",
            "editlink": "removeLink",
            "removelink": "openLink",
            "openimagelink": "editLink",
            "editimagelink": "removeLink",
            "removeimagelink": "gambar",
            "image": "menggantikan",
            "replace": "menyelaraskan",
            "align": "keterangan",
            "caption": "keluarkan",
            "remove": "insertLink",
            "insertlink": "paparan",
            "display": "altTeks",
            "alttext": "dimensi",
            "dimension": "skrin penuh",
            "fullscreen": "memaksimumkan",
            "maximize": "meminimumkan",
            "minimize": "lowerCase",
            "lowercase": "uppercase",
            "uppercase": "cetak",
            "print": "format",
            "formats": "kod sumber",
            "sourcecode": "pratonton",
            "preview": "pemandangan",
            "viewside": "masukkan kod",
            "insertcode": "Align Kiri",
            "justifyLeft": "Align Centre",
            "justifyCenter": "Align Right",
            "justifyRight": "Align Justify",
            "justifyFull": "Nama fon",
            "fontName": "Saiz huruf",
            "fontSize": "Warna fon",
            "fontColor": "Warna latar belakang",
            "backgroundColor": "berani",
            "bold": "italik",
            "italic": "garis bawah",
            "underline": "menyerang",
            "strikethrough": "potong",
            "cut": "salinan",
            "copy": "tampal",
            "paste": "indent",
            "indent": "langgar",
            "outdent": "undo",
            "undo": "buat semula",
            "redo": "superskrip",
            "superscript": "subskrip",
            "subscript": "Masukkan Hyperlink",
            "createLink": "Pautan Terbuka",
            "openLink": "Edit Pautan",
            "editLink": "Keluarkan Pautan",
            "removeLink": "Masukkan Pautan",
            "insertLink": "Teks alternatif",
            "altText": "Kes Rendah",
            "lowerCase": "Kes atas",
            "upperCase": "Masukkan kod",
            "insertCode": "Teks Paparan",
            "linkText": "Petua alat",
            "linkTooltipLabel": "Alamat Web",
            "linkWebUrl": "http://example.com",
            "linkurl": "Buka Pautan dalam Tetingkap Baru",
            "linkOpenInNewWindow": "Masukkan Pautan",
            "linkHeader": "Masukkan",
            "dialogInsert": "Batalkan",
            "dialogCancel": "Kemas kini",
            "dialogUpdate": "Masukkan Imej",
            "imageHeader": "Anda juga boleh menyediakan pautan dari web",
            "imageLinkHeader": "Sila berikan URL untuk imej anda",
            "mdimageLink": "Drop imej di sini atau semak imbas untuk dimuat naik",
            "imageUploadMessage": "Klik di sini untuk memuat naik",
            "imageDeviceUploadMessage": "Teks alternatif",
            "imageAlternateText": "Teks alternatif",
            "alternateHeader": "Semak imbas",
            "browse": "http://example.com/image.png",
            "imageUrl": "Keterangan",
            "imageCaption": "Saiz gambar",
            "imageSizeHeader": "Ketinggian",
            "imageHeight": "Lebar",
            "imageWidth": "Masukkan Teks",
            "textPlaceholder": "Jumlah keseluruhan"
        },
        "pivotview": {
            "grandTotal": "Jumlah",
            "total": "Nilai",
            "value": "Tiada nilai",
            "noValue": "Row",
            "row": "Kolum",
            "column": "Runtuh",
            "collapse": "Perluas",
            "expand": "Letakkan baris di sini",
            "rowAxisPrompt": "Letakkan ruangan di sini",
            "columnAxisPrompt": "Nilai drop di sini",
            "valueAxisPrompt": "Drop penapis di sini",
            "filterAxisPrompt": "Penapis",
            "filter": "Ditapis",
            "filtered": "Isih",
            "sort": "Penapis",
            "filters": "Baris",
            "rows": "Lajur",
            "columns": "Nilai",
            "values": "Tutup",
            "close": "Batalkan",
            "cancel": "Padam",
            "delete": "Medan yang dikira",
            "calculatedField": "Buat Lapangan Yang Dihitung",
            "createCalculatedField": "Masukkan nama medan",
            "fieldName": "Ralat",
            "error": "Nama formula atau nama lapangan tidak sah.",
            "invalidFormula": "Contoh: ('Sum (Order_Count)' + 'Sum (In_Stock)') * 250",
            "dropText": "Tambah medan dan edit formula di sini.",
            "dropTextMobile": "Medan yang dihitung tidak boleh ditempatkan di mana-mana rantau lain kecuali paksi nilai.",
            "dropAction": "Amaran",
            "alert": "Amaran",
            "warning": "okey",
            "ok": "Carian",
            "search": "Seret",
            "drag": "Keluarkan",
            "remove": "Jumlah",
            "sum": "Purata",
            "average": "Kira",
            "count": "Min",
            "min": "Maks",
            "max": "Semua Bidang",
            "allFields": "Formula",
            "formula": "Tambah ke Baris",
            "addToRow": "Tambah ke Lajur",
            "addToColumn": "Tambah ke Nilai",
            "addToValue": "Tambah ke Penapis",
            "addToFilter": "tiada rekod untuk dipaparkan",
            "emptyData": "Medan telah wujud dalam nama ini. Sila masukkan nama lain.",
            "fieldExist": "Medan pengiraan sudah ada dalam nama ini. Adakah anda ingin menggantikannya?",
            "confirmText": "Tiada perlawanan",
            "noMatches": "Nilai ringkasan oleh",
            "format": "Edit",
            "edit": "Jelas",
            "clear": "Seret dan lepaskan medan untuk formula",
            "formulaField": "Seret medan ke formula",
            "dragField": "Jelas",
            "clearFilter": "oleh",
            "by": "Masukkan nilai",
            "enterValue": "Masukkan tarikh",
            "chooseDate": "Sama",
            "Equals": "Tidak Sama",
            "DoesNotEquals": "Bermula dengan",
            "BeginWith": "Tidak Bermula Dengan",
            "DoesNotBeginWith": "Berakhir Dengan",
            "EndsWith": "Tidak Berakhir Dengan",
            "DoesNotEndsWith": "Mengandungi",
            "Contains": "Tidak mengandungi",
            "DoesNotContains": "Lebih besar daripada",
            "GreaterThan": "Lebih daripada atau sama",
            "GreaterThanOrEqualTo": "Kurang daripada",
            "LessThan": "Kurang Daripada Atau Bersamaan",
            "LessThanOrEqualTo": "Antara",
            "Between": "Bukan Antara",
            "NotBetween": "Sebelum ini",
            "Before": "Sebelum Atau Sama Kepada",
            "BeforeOrEqualTo": "Selepas",
            "After": "Selepas Atau Sama Untuk",
            "AfterOrEqualTo": "Ahli",
            "member": "Label",
            "label": "Tarikh",
            "date": "Tunjukkan item yang labelnya",
            "labelTextContent": "Tunjukkan item yang tarikhnya dipaparkan",
            "dateTextContent": "Tunjukkan item yang mana",
            "valueTextContent": "dan",
            "And": "Pemformatan Bersyarat",
            "conditionalFormating": "MEMOHON",
            "apply": "Tambah Keadaan",
            "condition": "Format",
            "formatLabel": "Senarai Medan Pivot"
        },
        "pivotfieldlist": {
            "staticFieldList": "Senarai Medan",
            "fieldList": "Drop penapis di sini",
            "dropFilterPrompt": "Letakkan ruangan di sini",
            "dropColPrompt": "Letakkan baris di sini",
            "dropRowPrompt": "Nilai drop di sini",
            "dropValPrompt": "Tambah medan di sini",
            "addPrompt": "Pilih medan",
            "adaptiveFieldHeader": "Seret medan antara paksi di bawah:",
            "centerHeader": "Tambah",
            "add": "Seret",
            "drag": "Penapis",
            "filter": "Ditapis",
            "filtered": "Isih",
            "sort": "Keluarkan",
            "remove": "Penapis",
            "filters": "Baris",
            "rows": "Lajur",
            "columns": "Nilai",
            "values": "Medan yang dikira",
            "calculatedField": "Buat Lapangan Yang Dihitung",
            "createCalculatedField": "Masukkan nama medan",
            "fieldName": "Ralat",
            "error": "Nama formula atau nama lapangan tidak sah.",
            "invalidFormula": "Contoh: ('Sum (Order_Count)' + 'Sum (In_Stock)') * 250",
            "dropText": "Tambah medan dan edit formula di sini.",
            "dropTextMobile": "Medan yang dihitung tidak boleh ditempatkan di mana-mana rantau lain kecuali paksi nilai.",
            "dropAction": "Carian",
            "search": "Tutup",
            "close": "Batalkan",
            "cancel": "Padam",
            "delete": "Amaran",
            "alert": "Amaran",
            "warning": "okey",
            "ok": "Jumlah",
            "sum": "Purata",
            "average": "Kira",
            "count": "Min",
            "min": "Maks",
            "max": "Semua Bidang",
            "allFields": "Formula",
            "formula": "Medan telah wujud dalam nama ini. Sila masukkan nama lain.",
            "fieldExist": "Medan pengiraan sudah ada dalam nama ini. Adakah anda ingin menggantikannya?",
            "confirmText": "Tiada perlawanan",
            "noMatches": "Nilai ringkasan oleh",
            "format": "Edit",
            "edit": "Jelas",
            "clear": "Seret dan lepaskan medan untuk formula",
            "formulaField": "Seret medan ke formula",
            "dragField": "Jelas",
            "clearFilter": "oleh",
            "by": "Masukkan nilai",
            "enterValue": "Masukkan tarikh",
            "chooseDate": "Sama",
            "Equals": "Tidak Sama",
            "DoesNotEquals": "Bermula dengan",
            "BeginWith": "Tidak Bermula Dengan",
            "DoesNotBeginWith": "Berakhir Dengan",
            "EndsWith": "Tidak Berakhir Dengan",
            "DoesNotEndsWith": "Mengandungi",
            "Contains": "Tidak mengandungi",
            "DoesNotContains": "Lebih besar daripada",
            "GreaterThan": "Lebih daripada atau sama",
            "GreaterThanOrEqualTo": "Kurang daripada",
            "LessThan": "Kurang Daripada Atau Bersamaan",
            "LessThanOrEqualTo": "Antara",
            "Between": "Bukan Antara",
            "NotBetween": "Sebelum ini",
            "Before": "Sebelum Atau Sama Kepada",
            "BeforeOrEqualTo": "Selepas",
            "After": "Selepas Atau Sama Untuk",
            "AfterOrEqualTo": "Ahli",
            "member": "Label",
            "label": "Tarikh",
            "date": "Nilai",
            "value": "Tunjukkan item yang labelnya",
            "labelTextContent": "Tunjukkan item yang tarikhnya dipaparkan",
            "dateTextContent": "Tunjukkan item yang mana",
            "valueTextContent": "dan",
            "And": "MEMOHON",
            "apply": "Tutup"
        },
        "tab": {
            "closeButtonTitle": "Tiada rekod dijumpai"
        },
        "drop-down-base": {
            "noRecordsTemplate": "Permintaan Gagal",
            "actionFailureTemplate": "Tiada rekod dijumpai"
        },
        "multi-select": {
            "noRecordsTemplate": "Permintaan Gagal",
            "actionFailureTemplate": "+ $ {count} lebih banyak ..",
            "overflowCountTemplate": "Pilih semua",
            "selectAllText": "Nyahpilih Semua",
            "unSelectAllText": "Salinan"
        },
        "diagram": {
            "Copy": "Potong",
            "Cut": "Tampal",
            "Paste": "Undo",
            "Undo": "Redo",
            "Redo": "Pilih semua",
            "SelectAll": "Pengumpulan",
            "Grouping": "Kumpulan",
            "Group": "Un Kumpulan",
            "UnGroup": "Perintah",
            "Order": "Bawa ke hadapan",
            "BringToFront": "Pindah ke Hadapan",
            "MoveForward": "Hantar ke belakang",
            "SendToBack": "Hantar ke belakang",
            "SendBackward": "Zum"
        },
        "maps": {
            "Zoom": "Mengezum masuk",
            "ZoomIn": "Zum keluar",
            "ZoomOut": "Tetapkan semula",
            "Reset": "Pan",
            "Pan": "Tetapkan semula Zum",
            "ResetZoom": "Memohon"
        },
        "colorpicker": {
            "Apply": "Batalkan",
            "Cancel": "Mod Suis",
            "ModeSwitcher": "Semak imbas ..."
        },
        "uploader": {
            "Browse": "Jelas",
            "Clear": "Muat naik",
            "Upload": "Atau jatuhkan fail di sini",
            "dropFilesHint": "Saiz fail terlalu besar",
            "invalidMaxFileSize": "Saiz fail terlalu kecil",
            "invalidMinFileSize": "Jenis fail tidak dibenarkan",
            "invalidFileType": "Fail gagal dimuat naik",
            "uploadFailedMessage": "Fail dimuat naik berjaya",
            "uploadSuccessMessage": "Fail dikeluarkan dengan jayanya",
            "removedSuccessMessage": "Tidak dapat menghapus fail",
            "removedFailedMessage": "Memuat naik",
            "inProgress": "Sedia untuk memuat naik",
            "readyToUploadMessage": "Abort",
            "abort": "Keluarkan",
            "remove": "Batalkan",
            "cancel": "Padam fail",
            "delete": "Muat naik fail dijeda",
            "pauseUpload": "Jeda",
            "pause": "Teruskan",
            "resume": "Cuba semula",
            "retry": "Muat naik fail dibatalkan",
            "fileUploadCancel": "Nilai pertambahan"
        },
        "numerictextbox": {
            "incrementTitle": "Nilai penolakan",
            "decrementTitle": "Meningkat"
        },
        "slider": {
            "Increase": "Kurangkan",
            "Decrease": "Tutup"
        },
        "dialog": {
            "close": " "
        }
    }
}